viracitapada/__init__.py
viracitapada/py.typed
viracitapada-0.1.1.dist-info/METADATA
viracitapada-0.1.1.dist-info/WHEEL
viracitapada-0.1.1.dist-info/licenses/LICENSE
viracitapada-0.1.1.dist-info/RECORD
