Metadata-Version: 2.4
Name: viracitapada
Version: 0.1.1
Summary: Performs metrical analysis on ISO-15919-transliterated Sanskrit verses
Project-URL: Repository, https://github.com/VedaWebProject/viracitapada
Project-URL: Issues, https://github.com/VedaWebProject/viracitapada/issues
Author: bkis
Maintainer: bkis
License: MIT License
License-File: LICENSE
Keywords: library,metrical-analysis,metrical-parser,sanskrit
Classifier: Development Status :: 5 - Production/Stable
Classifier: Intended Audience :: Developers
Classifier: Intended Audience :: Education
Classifier: Intended Audience :: Science/Research
Classifier: License :: OSI Approved :: MIT License
Classifier: Operating System :: OS Independent
Classifier: Programming Language :: Python :: 3.10
Classifier: Programming Language :: Python :: 3.11
Classifier: Programming Language :: Python :: 3.12
Classifier: Topic :: Text Processing :: Linguistic
Requires-Python: >=3.10
